nanolib/__init__.py
nanolib/abc.py
nanolib/abc_async.py
nanolib/custom_types.py
nanolib/exceptions.py
nanolib/py.typed
nanolib/setup.py
nanolib/bitswap/__init__.py
nanolib/bitswap/block_store.py
nanolib/bitswap/chunker.py
nanolib/bitswap/cid.py
nanolib/bitswap/client.py
nanolib/bitswap/config.py
nanolib/bitswap/dag.py
nanolib/bitswap/dag_pb.py
nanolib/bitswap/errors.py
nanolib/bitswap/messages.py
nanolib/bitswap/pb/__init__.py
nanolib/bitswap/pb/bitswap_pb2.py
nanolib/bitswap/pb/bitswap_pb2.pyi
nanolib/bitswap/pb/dag_pb_pb2.py
nanolib/bitswap/pb/dag_pb_pb2.pyi
nanolib/bitswap/pb/unixfs_pb2.py
nanolib/bitswap/pb/unixfs_pb2.pyi
nanolib/crypto/__init__.py
nanolib/crypto/authenticated_encryption.py
nanolib/crypto/ecc.py
nanolib/crypto/ed25519.py
nanolib/crypto/exceptions.py
nanolib/crypto/key_exchange.py
nanolib/crypto/keys.py
nanolib/crypto/rsa.py
nanolib/crypto/secp256k1.py
nanolib/crypto/serialization.py
nanolib/crypto/x25519.py
nanolib/crypto/pb/__init__.py
nanolib/crypto/pb/crypto_pb2.py
nanolib/crypto/pb/crypto_pb2.pyi
nanolib/discovery/__init__.py
nanolib/discovery/bootstrap/__init__.py
nanolib/discovery/bootstrap/bootstrap.py
nanolib/discovery/bootstrap/utils.py
nanolib/discovery/events/__init__.py
nanolib/discovery/events/peerDiscovery.py
nanolib/discovery/mdns/__init__.py
nanolib/discovery/mdns/broadcaster.py
nanolib/discovery/mdns/listener.py
nanolib/discovery/mdns/mdns.py
nanolib/discovery/mdns/utils.py
nanolib/discovery/random_walk/__init__.py
nanolib/discovery/random_walk/config.py
nanolib/discovery/random_walk/exceptions.py
nanolib/discovery/random_walk/random_walk.py
nanolib/discovery/random_walk/rt_refresh_manager.py
nanolib/discovery/rendezvous/__init__.py
nanolib/discovery/rendezvous/client.py
nanolib/discovery/rendezvous/config.py
nanolib/discovery/rendezvous/discovery.py
nanolib/discovery/rendezvous/errors.py
nanolib/discovery/rendezvous/messages.py
nanolib/discovery/rendezvous/service.py
nanolib/discovery/rendezvous/pb/__init__.py
nanopy_chain-1.2.87.dist-info/METADATA
nanopy_chain-1.2.87.dist-info/WHEEL
nanopy_chain-1.2.87.dist-info/entry_points.txt
nanopy_chain-1.2.87.dist-info/top_level.txt
nanopy_chain-1.2.87.dist-info/RECORD
