Metadata-Version: 2.4
Name: nanopy-chain
Version: 1.2.87
Summary: A lightweight Ethereum-compatible blockchain fork with P2P networking
Home-page: https://github.com/Web3-League/blockchain-python
Author: NanoPy Team
Author-email: dev@nanopy.chain
Keywords: blockchain ethereum fork cryptocurrency smart-contracts
Classifier: Development Status :: 4 - Beta
Classifier: Intended Audience :: Developers
Classifier: License :: OSI Approved :: MIT License
Classifier: Programming Language :: Python :: 3
Classifier: Programming Language :: Python :: 3.10
Classifier: Programming Language :: Python :: 3.11
Classifier: Programming Language :: Python :: 3.12
Classifier: Topic :: Software Development :: Libraries
Classifier: Topic :: System :: Distributed Computing
Requires-Python: >=3.8
Requires-Dist: eth-account>=0.8.0
Requires-Dist: eth-keys>=0.4.0
Requires-Dist: eth-typing>=3.0.0
Requires-Dist: eth-utils>=2.0.0
Requires-Dist: eth-hash[pycryptodome]>=0.5.0
Requires-Dist: eth-bloom>=3.0.0
Requires-Dist: eth-abi>=4.0.0
Requires-Dist: eth-rlp>=0.3.0
Requires-Dist: rlp>=3.0.0
Requires-Dist: web3>=6.0.0
Requires-Dist: aiohttp>=3.8.0
Requires-Dist: websockets>=10.0
Requires-Dist: py-ecc>=6.0.0
Requires-Dist: pycryptodome>=3.15.0
Requires-Dist: ecdsa>=0.18.0
Requires-Dist: trie>=2.0.0
Requires-Dist: click>=8.0.0
Requires-Dist: rich>=12.0.0
Requires-Dist: python-dotenv>=0.20.0
Requires-Dist: multiaddr>=0.0.9
Requires-Dist: protobuf>=3.20.0
Requires-Dist: trio>=0.22.0
Requires-Dist: trio-typing>=0.10.0
Requires-Dist: cryptography>=3.4.0
Requires-Dist: lru-dict>=1.1.0
Requires-Dist: base58>=2.0.0
Requires-Dist: pynacl>=1.5.0
Requires-Dist: coincurve>=18.0.0
Requires-Dist: trio-websocket>=0.10.0
Requires-Dist: aioquic>=0.9.0
Requires-Dist: noiseprotocol>=0.3.0
Requires-Dist: py-multihash>=2.0.0
Requires-Dist: zeroconf>=0.50.0
Requires-Dist: miniupnpc>=2.2.0
Requires-Dist: fastecdsa>=2.0.0; sys_platform != "win32"
Requires-Dist: grpcio>=1.50.0
Requires-Dist: varint>=1.0.0
Requires-Dist: psutil>=5.9.0
Provides-Extra: dev
Requires-Dist: pytest>=8.0.0; extra == "dev"
Requires-Dist: pytest-asyncio>=0.23.0; extra == "dev"
Requires-Dist: black>=24.0.0; extra == "dev"
Requires-Dist: mypy>=1.8.0; extra == "dev"
Requires-Dist: ruff>=0.2.0; extra == "dev"
Dynamic: author
Dynamic: author-email
Dynamic: classifier
Dynamic: description
Dynamic: description-content-type
Dynamic: home-page
Dynamic: keywords
Dynamic: provides-extra
Dynamic: requires-dist
Dynamic: requires-python
Dynamic: summary
